hasso/__init__.py
hasso/file_format/__init__.py
hasso/file_format/csv_format/__init__.py
hasso/file_format/csv_format/argument.py
hasso/file_format/csv_format/dump_csv.py
hasso/file_format/csv_format/func_mode.py
hasso/file_format/csv_format/load_csv.py
hasso/file_format/csv_format/converter/__init__.py
hasso/file_format/csv_format/converter/default.py
hasso/file_format/csv_format/converter/func.py
hasso/file_format/csv_format/converter/levels.py
hasso/file_format/csv_format/converter/converters/__init__.py
hasso/file_format/csv_format/converter/converters/boolean_from_str.py
hasso/file_format/csv_format/converter/converters/boolean_to_str.py
hasso/file_format/csv_format/converter/converters/remove_blank_row.py
hasso/file_format/csv_format/converter/converters/replace_excel_return.py
hasso/file_format/csv_format/converter/converters/row_as_dict.py
hasso/file_format/csv_format/converter/converters/sort_table.py
hasso/file_format/csv_format/converter/converters/to_float_cell.py
hasso/file_format/csv_format/converter/converters/to_integer_cell.py
hasso/file_format/csv_format/converter/converters/to_null_str.py
hasso/file_format/csv_format/converter/converters/to_null_str_column.py
hasso/file_format/csv_format/converter/converters/trim_string_by_cell.py
hasso/file_format/csv_format/converter/converters/trim_string_by_column.py
hasso/table/__init__.py
hasso/table/table.py
hasso-0.0.6.dist-info/METADATA
hasso-0.0.6.dist-info/WHEEL
hasso-0.0.6.dist-info/licenses/LICENSE
hasso-0.0.6.dist-info/RECORD
